mindtrace/services/__init__.py
mindtrace/services/core/__init__.py
mindtrace/services/core/connection_manager.py
mindtrace/services/core/launcher.py
mindtrace/services/core/mcp_client_manager.py
mindtrace/services/core/middleware.py
mindtrace/services/core/service.py
mindtrace/services/core/types.py
mindtrace/services/core/utils.py
mindtrace/services/discord/__init__.py
mindtrace/services/discord/discord_client.py
mindtrace/services/discord/discord_service.py
mindtrace/services/discord/types.py
mindtrace/services/gateway/__init__.py
mindtrace/services/gateway/gateway.py
mindtrace/services/gateway/proxy_connection_manager.py
mindtrace/services/gateway/types.py
mindtrace/services/sample/echo_logging_service.py
mindtrace/services/samples/echo_mcp.py
mindtrace/services/samples/echo_service.py
mindtrace/services/samples/discord/custom_bot_client.py
mindtrace/services/samples/discord/custom_bot_service.py
mindtrace_services-0.8.0.dist-info/licenses/LICENSE
mindtrace_services-0.8.0.dist-info/METADATA
mindtrace_services-0.8.0.dist-info/WHEEL
mindtrace_services-0.8.0.dist-info/top_level.txt
mindtrace_services-0.8.0.dist-info/RECORD
