Metadata-Version: 2.4
Name: mindtrace-services
Version: 0.8.0
Summary: Service layer for Mindtrace
Author: Mindtrace Team
License-Expression: Apache-2.0
Project-URL: Homepage, https://mindtrace.ai
Project-URL: Repository, https://github.com/mindtrace/mindtrace/blob/main/mindtrace/services
Classifier: Programming Language :: Python :: 3
Classifier: Programming Language :: Python :: 3.12
License-File: LICENSE
Requires-Dist: mindtrace-core>=0.8.0
Requires-Dist: fastapi>=0.115.14
Requires-Dist: gunicorn>=23.0.0
Requires-Dist: httpx>=0.27.2
Requires-Dist: psutil>=5.9.0
Requires-Dist: requests>=2.28.0
Requires-Dist: structlog>=24.4.0
Requires-Dist: uvicorn>=0.34.3
Requires-Dist: aiohttp>=3.12.13
Requires-Dist: pydantic<2.12.0,>=2.8.0
Requires-Dist: fastmcp>=2.13.0
Requires-Dist: discord.py>=2.3.0
Dynamic: license-file
